LICENSE
README.md
setup.py
fastratelimiter/__init__.py
fastratelimiter/fastratelimiter.py
fastratelimiter.egg-info/PKG-INFO
fastratelimiter.egg-info/SOURCES.txt
fastratelimiter.egg-info/dependency_links.txt
fastratelimiter.egg-info/not-zip-safe
fastratelimiter.egg-info/top_level.txt
tests/test_fastratelimiter.py